py_zap/__init__.py
py_zap/constants.py
py_zap/py_zap.py
py_zap/search.py
py_zap/sorter.py
py_zap/utils.py
py_zap-1.2.2.dist-info/LICENSE.txt
py_zap-1.2.2.dist-info/METADATA
py_zap-1.2.2.dist-info/WHEEL
py_zap-1.2.2.dist-info/top_level.txt
py_zap-1.2.2.dist-info/RECORD
