Metadata-Version: 2.1
Name: py-zap
Version: 1.2.2
Summary: Python scraper for accessing ratings from tvbythenumbers.zap2it.com
Home-page: https://github.com/sharibarboza/py_zap
Author: sharibarboza
Author-email: barbozashari@gmail.com
License: MIT License
Download-URL: https://github.com/sharibarboza/py_zap/archive/1.0.0.tar.gz
Keywords: zap2it,ratings,tv
Platform: UNKNOWN
Requires-Dist: beautifulsoup4
Requires-Dist: requests (>=2.9.1)
